clock.v
`default_nettype none

module clock(i_clk, i_rst, o_clk);
    input wire i_clk;
    input wire i_rst;
    output reg o_clk;

    reg [10:0] counter;

    always @ (posedge i_clk, posedge i_rst) begin
        if (i_rst) begin
            counter <= 0;
            o_clk <= 0;
        end else if (counter == 1249) begin
            counter <= 0;
            o_clk <= 1;
        end else begin
            counter <= counter + 1;
            o_clk <= 0;
        end
    end
endmodule

clock-trace.vcd
$version Generated by VerilatedVcd $end
$timescale 1ps $end
 $scope module TOP $end
  $var wire 1 # i_clk $end
  $var wire 1 $ i_rst $end
  $var wire 1 % o_clk $end
  $scope module clock $end
   $var wire 1 # i_clk $end
   $var wire 1 $ i_rst $end
   $var wire 1 % o_clk $end
   $var wire 11 & counter [10:0] $end
  $upscope $end
 $upscope $end
$enddefinitions $end


#0
1#
0$
0%
b00000000000 &
#1
0#
#2
1#
b00000000001 &
#3
0#
#4
1#
b00000000010 &
#5
0#
#6
1#
b00000000011 &
#7
0#
#8
1#
b00000000100 &
#9
0#
#10
1#
b00000000101 &
#11
0#
#12
1#
b00000000110 &
#13
0#
#14
1#
b00000000111 &
#15
0#
#16
1#
b00000001000 &
#17
0#
#18
1#
b00000001001 &
#19
0#
#20
1#
b00000001010 &
#21
0#
#22
1#
b00000001011 &
#23
0#
#24
1#
b00000001100 &
#25
0#
#26
1#
b00000001101 &
#27
0#
#28
1#
b00000001110 &
#29
0#
#30
1#
b00000001111 &
#31
0#
#32
1#
b00000010000 &
#33
0#
#34
1#
b00000010001 &
#35
0#
#36
1#
b00000010010 &
#37
0#
#38
1#
b00000010011 &
#39
0#
#40
1#
b00000010100 &
#41
0#
#42
1#
b00000010101 &
#43
0#
#44
1#
b00000010110 &
#45
0#
#46
1#
b00000010111 &
#47
0#
#48
1#
b00000011000 &
#49
0#
#50
1#
b00000011001 &
#51
0#
#52
1#
b00000011010 &
#53
0#
#54
1#
b00000011011 &
#55
0#
#56
1#
b00000011100 &
#57
0#
#58
1#
b00000011101 &
#59
0#
#60
1#
b00000011110 &
#61
0#
#62
1#
b00000011111 &
#63
0#
#64
1#
b00000100000 &
#65
0#
#66
1#
b00000100001 &
#67
0#
#68
1#
b00000100010 &
#69
0#
#70
1#
b00000100011 &
#71
0#
#72
1#
b00000100100 &
#73
0#
#74
1#
b00000100101 &
#75
0#
#76
1#
b00000100110 &
#77
0#
#78
1#
b00000100111 &
#79
0#
#80
1#
b00000101000 &
#81
0#
#82
1#
b00000101001 &
#83
0#
#84
1#
b00000101010 &
#85
0#
#86
1#
b00000101011 &
#87
0#
#88
1#
b00000101100 &
#89
0#
#90
1#
b00000101101 &
#91
0#
#92
1#
b00000101110 &
#93
0#
#94
1#
b00000101111 &
#95
0#
#96
1#
b00000110000 &
#97
0#
#98
1#
b00000110001 &
#99
0#
#100
1#
b00000110010 &
#101
0#
#102
1#
b00000110011 &
#103
0#
#104
1#
b00000110100 &
#105
0#
#106
1#
b00000110101 &
#107
0#
#108
1#
b00000110110 &
#109
0#
#110
1#
b00000110111 &
#111
0#
#112
1#
b00000111000 &
#113
0#
#114
1#
b00000111001 &
#115
0#
#116
1#
b00000111010 &
#117
0#
#118
1#
b00000111011 &
#119
0#
#120
1#
b00000111100 &
#121
0#
#122
1#
b00000111101 &
#123
0#
#124
1#
b00000111110 &
#125
0#
#126
1#
b00000111111 &
#127
0#
#128
1#
b00001000000 &
#129
0#
#130
1#
b00001000001 &
#131
0#
#132
1#
b00001000010 &
#133
0#
#134
1#
b00001000011 &
#135
0#
#136
1#
b00001000100 &
#137
0#
#138
1#
b00001000101 &
#139
0#
#140
1#
b00001000110 &
#141
0#
#142
1#
b00001000111 &
#143
0#
#144
1#
b00001001000 &
#145
0#
#146
1#
b00001001001 &
#147
0#
#148
1#
b00001001010 &
#149
0#
#150
1#
b00001001011 &
#151
0#
#152
1#
b00001001100 &
#153
0#
#154
1#
b00001001101 &
#155
0#
#156
1#
b00001001110 &
#157
0#
#158
1#
b00001001111 &
#159
0#
#160
1#
b00001010000 &
#161
0#
#162
1#
b00001010001 &
#163
0#
#164
1#
b00001010010 &
#165
0#
#166
1#
b00001010011 &
#167
0#
#168
1#
b00001010100 &
#169
0#
#170
1#
b00001010101 &
#171
0#
#172
1#
b00001010110 &
#173
0#
#174
1#
b00001010111 &
#175
0#
#176
1#
b00001011000 &
#177
0#
#178
1#
b00001011001 &
#179
0#
#180
1#
b00001011010 &
#181
0#
#182
1#
b00001011011 &
#183
0#
#184
1#
b00001011100 &
#185
0#
#186
1#
b00001011101 &
#187
0#
#188
1#
b00001011110 &
#189
0#
#190
1#
b00001011111 &
#191
0#
#192
1#
b00001100000 &
#193
0#
#194
1#
b00001100001 &
#195
0#
#196
1#
b00001100010 &
#197
0#
#198
1#
b00001100011 &
#199
0#
#200
1#
b00001100100 &
#201
0#
#202
1#
b00001100101 &
#203
0#
#204
1#
b00001100110 &
#205
0#
#206
1#
b00001100111 &
#207
0#
#208
1#
b00001101000 &
#209
0#
#210
1#
b00001101001 &
#211
0#
#212
1#
b00001101010 &
#213
0#
#214
1#
b00001101011 &
#215
0#
#216
1#
b00001101100 &
#217
0#
#218
1#
b00001101101 &
#219
0#
#220
1#
b00001101110 &
#221
0#
#222
1#
b00001101111 &
#223
0#
#224
1#
b00001110000 &
#225
0#
#226
1#
b00001110001 &
#227
0#
#228
1#
b00001110010 &
#229
0#
#230
1#
b00001110011 &
#231
0#
#232
1#
b00001110100 &
#233
0#
#234
1#
b00001110101 &
#235
0#
#236
1#
b00001110110 &
#237
0#
#238
1#
b00001110111 &
#239
0#
#240
1#
b00001111000 &
#241
0#
#242
1#
b00001111001 &
#243
0#
#244
1#
b00001111010 &
#245
0#
#246
1#
b00001111011 &
#247
0#
#248
1#
b00001111100 &
#249
0#
#250
1#
b00001111101 &
#251
0#
#252
1#
b00001111110 &
#253
0#
#254
1#
b00001111111 &
#255
0#
#256
1#
b00010000000 &
#257
0#
#258
1#
b00010000001 &
#259
0#
#260
1#
b00010000010 &
#261
0#
#262
1#
b00010000011 &
#263
0#
#264
1#
b00010000100 &
#265
0#
#266
1#
b00010000101 &
#267
0#
#268
1#
b00010000110 &
#269
0#
#270
1#
b00010000111 &
#271
0#
#272
1#
b00010001000 &
#273
0#
#274
1#
b00010001001 &
#275
0#
#276
1#
b00010001010 &
#277
0#
#278
1#
b00010001011 &
#279
0#
#280
1#
b00010001100 &
#281
0#
#282
1#
b00010001101 &
#283
0#
#284
1#
b00010001110 &
#285
0#
#286
1#
b00010001111 &
#287
0#
#288
1#
b00010010000 &
#289
0#
#290
1#
b00010010001 &
#291
0#
#292
1#
b00010010010 &
#293
0#
#294
1#
b00010010011 &
#295
0#
#296
1#
b00010010100 &
#297
0#
#298
1#
b00010010101 &
#299
0#
#300
1#
b00010010110 &
#301
0#
#302
1#
b00010010111 &
#303
0#
#304
1#
b00010011000 &
#305
0#
#306
1#
b00010011001 &
#307
0#
#308
1#
b00010011010 &
#309
0#
#310
1#
b00010011011 &
#311
0#
#312
1#
b00010011100 &
#313
0#
#314
1#
b00010011101 &
#315
0#
#316
1#
b00010011110 &
#317
0#
#318
1#
b00010011111 &
#319
0#
#320
1#
b00010100000 &
#321
0#
#322
1#
b00010100001 &
#323
0#
#324
1#
b00010100010 &
#325
0#
#326
1#
b00010100011 &
#327
0#
#328
1#
b00010100100 &
#329
0#
#330
1#
b00010100101 &
#331
0#
#332
1#
b00010100110 &
#333
0#
#334
1#
b00010100111 &
#335
0#
#336
1#
b00010101000 &
#337
0#
#338
1#
b00010101001 &
#339
0#
#340
1#
b00010101010 &
#341
0#
#342
1#
b00010101011 &
#343
0#
#344
1#
b00010101100 &
#345
0#
#346
1#
b00010101101 &
#347
0#
#348
1#
b00010101110 &
#349
0#
#350
1#
b00010101111 &
#351
0#
#352
1#
b00010110000 &
#353
0#
#354
1#
b00010110001 &
#355
0#
#356
1#
b00010110010 &
#357
0#
#358
1#
b00010110011 &
#359
0#
#360
1#
b00010110100 &
#361
0#
#362
1#
b00010110101 &
#363
0#
#364
1#
b00010110110 &
#365
0#
#366
1#
b00010110111 &
#367
0#
#368
1#
b00010111000 &
#369
0#
#370
1#
b00010111001 &
#371
0#
#372
1#
b00010111010 &
#373
0#
#374
1#
b00010111011 &
#375
0#
#376
1#
b00010111100 &
#377
0#
#378
1#
b00010111101 &
#379
0#
#380
1#
b00010111110 &
#381
0#
#382
1#
b00010111111 &
#383
0#
#384
1#
b00011000000 &
#385
0#
#386
1#
b00011000001 &
#387
0#
#388
1#
b00011000010 &
#389
0#
#390
1#
b00011000011 &
#391
0#
#392
1#
b00011000100 &
#393
0#
#394
1#
b00011000101 &
#395
0#
#396
1#
b00011000110 &
#397
0#
#398
1#
b00011000111 &
#399
0#
#400
1#
b00011001000 &
#401
0#
#402
1#
b00011001001 &
#403
0#
#404
1#
b00011001010 &
#405
0#
#406
1#
b00011001011 &
#407
0#
#408
1#
b00011001100 &
#409
0#
#410
1#
b00011001101 &
#411
0#
#412
1#
b00011001110 &
#413
0#
#414
1#
b00011001111 &
#415
0#
#416
1#
b00011010000 &
#417
0#
#418
1#
b00011010001 &
#419
0#
#420
1#
b00011010010 &
#421
0#
#422
1#
b00011010011 &
#423
0#
#424
1#
b00011010100 &
#425
0#
#426
1#
b00011010101 &
#427
0#
#428
1#
b00011010110 &
#429
0#
#430
1#
b00011010111 &
#431
0#
#432
1#
b00011011000 &
#433
0#
#434
1#
b00011011001 &
#435
0#
#436
1#
b00011011010 &
#437
0#
#438
1#
b00011011011 &
#439
0#
#440
1#
b00011011100 &
#441
0#
#442
1#
b00011011101 &
#443
0#
#444
1#
b00011011110 &
#445
0#
#446
1#
b00011011111 &
#447
0#
#448
1#
b00011100000 &
#449
0#
#450
1#
b00011100001 &
#451
0#
#452
1#
b00011100010 &
#453
0#
#454
1#
b00011100011 &
#455
0#
#456
1#
b00011100100 &
#457
0#
#458
1#
b00011100101 &
#459
0#
#460
1#
b00011100110 &
#461
0#
#462
1#
b00011100111 &
#463
0#
#464
1#
b00011101000 &
#465
0#
#466
1#
b00011101001 &
#467
0#
#468
1#
b00011101010 &
#469
0#
#470
1#
b00011101011 &
#471
0#
#472
1#
b00011101100 &
#473
0#
#474
1#
b00011101101 &
#475
0#
#476
1#
b00011101110 &
#477
0#
#478
1#
b00011101111 &
#479
0#
#480
1#
b00011110000 &
#481
0#
#482
1#
b00011110001 &
#483
0#
#484
1#
b00011110010 &
#485
0#
#486
1#
b00011110011 &
#487
0#
#488
1#
b00011110100 &
#489
0#
#490
1#
b00011110101 &
#491
0#
#492
1#
b00011110110 &
#493
0#
#494
1#
b00011110111 &
#495
0#
#496
1#
b00011111000 &
#497
0#
#498
1#
b00011111001 &
#499
0#
#500
1#
b00011111010 &
#501
0#
#502
1#
b00011111011 &
#503
0#
#504
1#
b00011111100 &
#505
0#
#506
1#
b00011111101 &
#507
0#
#508
1#
b00011111110 &
#509
0#
#510
1#
b00011111111 &
#511
0#
#512
1#
b00100000000 &
#513
0#
#514
1#
b00100000001 &
#515
0#
#516
1#
b00100000010 &
#517
0#
#518
1#
b00100000011 &
#519
0#
#520
1#
b00100000100 &
#521
0#
#522
1#
b00100000101 &
#523
0#
#524
1#
b00100000110 &
#525
0#
#526
1#
b00100000111 &
#527
0#
#528
1#
b00100001000 &
#529
0#
#530
1#
b00100001001 &
#531
0#
#532
1#
b00100001010 &
#533
0#
#534
1#
b00100001011 &
#535
0#
#536
1#
b00100001100 &
#537
0#
#538
1#
b00100001101 &
#539
0#
#540
1#
b00100001110 &
#541
0#
#542
1#
b00100001111 &
#543
0#
#544
1#
b00100010000 &
#545
0#
#546
1#
b00100010001 &
#547
0#
#548
1#
b00100010010 &
#549
0#
#550
1#
b00100010011 &
#551
0#
#552
1#
b00100010100 &
#553
0#
#554
1#
b00100010101 &
#555
0#
#556
1#
b00100010110 &
#557
0#
#558
1#
b00100010111 &
#559
0#
#560
1#
b00100011000 &
#561
0#
#562
1#
b00100011001 &
#563
0#
#564
1#
b00100011010 &
#565
0#
#566
1#
b00100011011 &
#567
0#
#568
1#
b00100011100 &
#569
0#
#570
1#
b00100011101 &
#571
0#
#572
1#
b00100011110 &
#573
0#
#574
1#
b00100011111 &
#575
0#
#576
1#
b00100100000 &
#577
0#
#578
1#
b00100100001 &
#579
0#
#580
1#
b00100100010 &
#581
0#
#582
1#
b00100100011 &
#583
0#
#584
1#
b00100100100 &
#585
0#
#586
1#
b00100100101 &
#587
0#
#588
1#
b00100100110 &
#589
0#
#590
1#
b00100100111 &
#591
0#
#592
1#
b00100101000 &
#593
0#
#594
1#
b00100101001 &
#595
0#
#596
1#
b00100101010 &
#597
0#
#598
1#
b00100101011 &
#599
0#
#600
1#
b00100101100 &
#601
0#
#602
1#
b00100101101 &
#603
0#
#604
1#
b00100101110 &
#605
0#
#606
1#
b00100101111 &
#607
0#
#608
1#
b00100110000 &
#609
0#
#610
1#
b00100110001 &
#611
0#
#612
1#
b00100110010 &
#613
0#
#614
1#
b00100110011 &
#615
0#
#616
1#
b00100110100 &
#617
0#
#618
1#
b00100110101 &
#619
0#
#620
1#
b00100110110 &
#621
0#
#622
1#
b00100110111 &
#623
0#
#624
1#
b00100111000 &
#625
0#
#626
1#
b00100111001 &
#627
0#
#628
1#
b00100111010 &
#629
0#
#630
1#
b00100111011 &
#631
0#
#632
1#
b00100111100 &
#633
0#
#634
1#
b00100111101 &
#635
0#
#636
1#
b00100111110 &
#637
0#
#638
1#
b00100111111 &
#639
0#
#640
1#
b00101000000 &
#641
0#
#642
1#
b00101000001 &
#643
0#
#644
1#
b00101000010 &
#645
0#
#646
1#
b00101000011 &
#647
0#
#648
1#
b00101000100 &
#649
0#
#650
1#
b00101000101 &
#651
0#
#652
1#
b00101000110 &
#653
0#
#654
1#
b00101000111 &
#655
0#
#656
1#
b00101001000 &
#657
0#
#658
1#
b00101001001 &
#659
0#
#660
1#
b00101001010 &
#661
0#
#662
1#
b00101001011 &
#663
0#
#664
1#
b00101001100 &
#665
0#
#666
1#
b00101001101 &
#667
0#
#668
1#
b00101001110 &
#669
0#
#670
1#
b00101001111 &
#671
0#
#672
1#
b00101010000 &
#673
0#
#674
1#
b00101010001 &
#675
0#
#676
1#
b00101010010 &
#677
0#
#678
1#
b00101010011 &
#679
0#
#680
1#
b00101010100 &
#681
0#
#682
1#
b00101010101 &
#683
0#
#684
1#
b00101010110 &
#685
0#
#686
1#
b00101010111 &
#687
0#
#688
1#
b00101011000 &
#689
0#
#690
1#
b00101011001 &
#691
0#
#692
1#
b00101011010 &
#693
0#
#694
1#
b00101011011 &
#695
0#
#696
1#
b00101011100 &
#697
0#
#698
1#
b00101011101 &
#699
0#
#700
1#
b00101011110 &
#701
0#
#702
1#
b00101011111 &
#703
0#
#704
1#
b00101100000 &
#705
0#
#706
1#
b00101100001 &
#707
0#
#708
1#
b00101100010 &
#709
0#
#710
1#
b00101100011 &
#711
0#
#712
1#
b00101100100 &
#713
0#
#714
1#
b00101100101 &
#715
0#
#716
1#
b00101100110 &
#717
0#
#718
1#
b00101100111 &
#719
0#
#720
1#
b00101101000 &
#721
0#
#722
1#
b00101101001 &
#723
0#
#724
1#
b00101101010 &
#725
0#
#726
1#
b00101101011 &
#727
0#
#728
1#
b00101101100 &
#729
0#
#730
1#
b00101101101 &
#731
0#
#732
1#
b00101101110 &
#733
0#
#734
1#
b00101101111 &
#735
0#
#736
1#
b00101110000 &
#737
0#
#738
1#
b00101110001 &
#739
0#
#740
1#
b00101110010 &
#741
0#
#742
1#
b00101110011 &
#743
0#
#744
1#
b00101110100 &
#745
0#
#746
1#
b00101110101 &
#747
0#
#748
1#
b00101110110 &
#749
0#
#750
1#
b00101110111 &
#751
0#
#752
1#
b00101111000 &
#753
0#
#754
1#
b00101111001 &
#755
0#
#756
1#
b00101111010 &
#757
0#
#758
1#
b00101111011 &
#759
0#
#760
1#
b00101111100 &
#761
0#
#762
1#
b00101111101 &
#763
0#
#764
1#
b00101111110 &
#765
0#
#766
1#
b00101111111 &
#767
0#
#768
1#
b00110000000 &
#769
0#
#770
1#
b00110000001 &
#771
0#
#772
1#
b00110000010 &
#773
0#
#774
1#
b00110000011 &
#775
0#
#776
1#
b00110000100 &
#777
0#
#778
1#
b00110000101 &
#779
0#
#780
1#
b00110000110 &
#781
0#
#782
1#
b00110000111 &
#783
0#
#784
1#
b00110001000 &
#785
0#
#786
1#
b00110001001 &
#787
0#
#788
1#
b00110001010 &
#789
0#
#790
1#
b00110001011 &
#791
0#
#792
1#
b00110001100 &
#793
0#
#794
1#
b00110001101 &
#795
0#
#796
1#
b00110001110 &
#797
0#
#798
1#
b00110001111 &
#799
0#
#800
1#
b00110010000 &
#801
0#
#802
1#
b00110010001 &
#803
0#
#804
1#
b00110010010 &
#805
0#
#806
1#
b00110010011 &
#807
0#
#808
1#
b00110010100 &
#809
0#
#810
1#
b00110010101 &
#811
0#
#812
1#
b00110010110 &
#813
0#
#814
1#
b00110010111 &
#815
0#
#816
1#
b00110011000 &
#817
0#
#818
1#
b00110011001 &
#819
0#
#820
1#
b00110011010 &
#821
0#
#822
1#
b00110011011 &
#823
0#
#824
1#
b00110011100 &
#825
0#
#826
1#
b00110011101 &
#827
0#
#828
1#
b00110011110 &
#829
0#
#830
1#
b00110011111 &
#831
0#
#832
1#
b00110100000 &
#833
0#
#834
1#
b00110100001 &
#835
0#
#836
1#
b00110100010 &
#837
0#
#838
1#
b00110100011 &
#839
0#
#840
1#
b00110100100 &
#841
0#
#842
1#
b00110100101 &
#843
0#
#844
1#
b00110100110 &
#845
0#
#846
1#
b00110100111 &
#847
0#
#848
1#
b00110101000 &
#849
0#
#850
1#
b00110101001 &
#851
0#
#852
1#
b00110101010 &
#853
0#
#854
1#
b00110101011 &
#855
0#
#856
1#
b00110101100 &
#857
0#
#858
1#
b00110101101 &
#859
0#
#860
1#
b00110101110 &
#861
0#
#862
1#
b00110101111 &
#863
0#
#864
1#
b00110110000 &
#865
0#
#866
1#
b00110110001 &
#867
0#
#868
1#
b00110110010 &
#869
0#
#870
1#
b00110110011 &
#871
0#
#872
1#
b00110110100 &
#873
0#
#874
1#
b00110110101 &
#875
0#
#876
1#
b00110110110 &
#877
0#
#878
1#
b00110110111 &
#879
0#
#880
1#
b00110111000 &
#881
0#
#882
1#
b00110111001 &
#883
0#
#884
1#
b00110111010 &
#885
0#
#886
1#
b00110111011 &
#887
0#
#888
1#
b00110111100 &
#889
0#
#890
1#
b00110111101 &
#891
0#
#892
1#
b00110111110 &
#893
0#
#894
1#
b00110111111 &
#895
0#
#896
1#
b00111000000 &
#897
0#
#898
1#
b00111000001 &
#899
0#
#900
1#
b00111000010 &
#901
0#
#902
1#
b00111000011 &
#903
0#
#904
1#
b00111000100 &
#905
0#
#906
1#
b00111000101 &
#907
0#
#908
1#
b00111000110 &
#909
0#
#910
1#
b00111000111 &
#911
0#
#912
1#
b00111001000 &
#913
0#
#914
1#
b00111001001 &
#915
0#
#916
1#
b00111001010 &
#917
0#
#918
1#
b00111001011 &
#919
0#
#920
1#
b00111001100 &
#921
0#
#922
1#
b00111001101 &
#923
0#
#924
1#
b00111001110 &
#925
0#
#926
1#
b00111001111 &
#927
0#
#928
1#
b00111010000 &
#929
0#
#930
1#
b00111010001 &
#931
0#
#932
1#
b00111010010 &
#933
0#
#934
1#
b00111010011 &
#935
0#
#936
1#
b00111010100 &
#937
0#
#938
1#
b00111010101 &
#939
0#
#940
1#
b00111010110 &
#941
0#
#942
1#
b00111010111 &
#943
0#
#944
1#
b00111011000 &
#945
0#
#946
1#
b00111011001 &
#947
0#
#948
1#
b00111011010 &
#949
0#
#950
1#
b00111011011 &
#951
0#
#952
1#
b00111011100 &
#953
0#
#954
1#
b00111011101 &
#955
0#
#956
1#
b00111011110 &
#957
0#
#958
1#
b00111011111 &
#959
0#
#960
1#
b00111100000 &
#961
0#
#962
1#
b00111100001 &
#963
0#
#964
1#
b00111100010 &
#965
0#
#966
1#
b00111100011 &
#967
0#
#968
1#
b00111100100 &
#969
0#
#970
1#
b00111100101 &
#971
0#
#972
1#
b00111100110 &
#973
0#
#974
1#
b00111100111 &
#975
0#
#976
1#
b00111101000 &
#977
0#
#978
1#
b00111101001 &
#979
0#
#980
1#
b00111101010 &
#981
0#
#982
1#
b00111101011 &
#983
0#
#984
1#
b00111101100 &
#985
0#
#986
1#
b00111101101 &
#987
0#
#988
1#
b00111101110 &
#989
0#
#990
1#
b00111101111 &
#991
0#
#992
1#
b00111110000 &
#993
0#
#994
1#
b00111110001 &
#995
0#
#996
1#
b00111110010 &
#997
0#
#998
1#
b00111110011 &
#999
0#
#1000
1#
b00111110100 &
#1001
0#
#1002
1#
b00111110101 &
#1003
0#
#1004
1#
b00111110110 &
#1005
0#
#1006
1#
b00111110111 &
#1007
0#
#1008
1#
b00111111000 &
#1009
0#
#1010
1#
b00111111001 &
#1011
0#
#1012
1#
b00111111010 &
#1013
0#
#1014
1#
b00111111011 &
#1015
0#
#1016
1#
b00111111100 &
#1017
0#
#1018
1#
b00111111101 &
#1019
0#
#1020
1#
b00111111110 &
#1021
0#
#1022
1#
b00111111111 &
#1023
0#
#1024
1#
b01000000000 &
#1025
0#
#1026
1#
b01000000001 &
#1027
0#
#1028
1#
b01000000010 &
#1029
0#
#1030
1#
b01000000011 &
#1031
0#
#1032
1#
b01000000100 &
#1033
0#
#1034
1#
b01000000101 &
#1035
0#
#1036
1#
b01000000110 &
#1037
0#
#1038
1#
b01000000111 &
#1039
0#
#1040
1#
b01000001000 &
#1041
0#
#1042
1#
b01000001001 &
#1043
0#
#1044
1#
b01000001010 &
#1045
0#
#1046
1#
b01000001011 &
#1047
0#
#1048
1#
b01000001100 &
#1049
0#
#1050
1#
b01000001101 &
#1051
0#
#1052
1#
b01000001110 &
#1053
0#
#1054
1#
b01000001111 &
#1055
0#
#1056
1#
b01000010000 &
#1057
0#
#1058
1#
b01000010001 &
#1059
0#
#1060
1#
b01000010010 &
#1061
0#
#1062
1#
b01000010011 &
#1063
0#
#1064
1#
b01000010100 &
#1065
0#
#1066
1#
b01000010101 &
#1067
0#
#1068
1#
b01000010110 &
#1069
0#
#1070
1#
b01000010111 &
#1071
0#
#1072
1#
b01000011000 &
#1073
0#
#1074
1#
b01000011001 &
#1075
0#
#1076
1#
b01000011010 &
#1077
0#
#1078
1#
b01000011011 &
#1079
0#
#1080
1#
b01000011100 &
#1081
0#
#1082
1#
b01000011101 &
#1083
0#
#1084
1#
b01000011110 &
#1085
0#
#1086
1#
b01000011111 &
#1087
0#
#1088
1#
b01000100000 &
#1089
0#
#1090
1#
b01000100001 &
#1091
0#
#1092
1#
b01000100010 &
#1093
0#
#1094
1#
b01000100011 &
#1095
0#
#1096
1#
b01000100100 &
#1097
0#
#1098
1#
b01000100101 &
#1099
0#
#1100
1#
b01000100110 &
#1101
0#
#1102
1#
b01000100111 &
#1103
0#
#1104
1#
b01000101000 &
#1105
0#
#1106
1#
b01000101001 &
#1107
0#
#1108
1#
b01000101010 &
#1109
0#
#1110
1#
b01000101011 &
#1111
0#
#1112
1#
b01000101100 &
#1113
0#
#1114
1#
b01000101101 &
#1115
0#
#1116
1#
b01000101110 &
#1117
0#
#1118
1#
b01000101111 &
#1119
0#
#1120
1#
b01000110000 &
#1121
0#
#1122
1#
b01000110001 &
#1123
0#
#1124
1#
b01000110010 &
#1125
0#
#1126
1#
b01000110011 &
#1127
0#
#1128
1#
b01000110100 &
#1129
0#
#1130
1#
b01000110101 &
#1131
0#
#1132
1#
b01000110110 &
#1133
0#
#1134
1#
b01000110111 &
#1135
0#
#1136
1#
b01000111000 &
#1137
0#
#1138
1#
b01000111001 &
#1139
0#
#1140
1#
b01000111010 &
#1141
0#
#1142
1#
b01000111011 &
#1143
0#
#1144
1#
b01000111100 &
#1145
0#
#1146
1#
b01000111101 &
#1147
0#
#1148
1#
b01000111110 &
#1149
0#
#1150
1#
b01000111111 &
#1151
0#
#1152
1#
b01001000000 &
#1153
0#
#1154
1#
b01001000001 &
#1155
0#
#1156
1#
b01001000010 &
#1157
0#
#1158
1#
b01001000011 &
#1159
0#
#1160
1#
b01001000100 &
#1161
0#
#1162
1#
b01001000101 &
#1163
0#
#1164
1#
b01001000110 &
#1165
0#
#1166
1#
b01001000111 &
#1167
0#
#1168
1#
b01001001000 &
#1169
0#
#1170
1#
b01001001001 &
#1171
0#
#1172
1#
b01001001010 &
#1173
0#
#1174
1#
b01001001011 &
#1175
0#
#1176
1#
b01001001100 &
#1177
0#
#1178
1#
b01001001101 &
#1179
0#
#1180
1#
b01001001110 &
#1181
0#
#1182
1#
b01001001111 &
#1183
0#
#1184
1#
b01001010000 &
#1185
0#
#1186
1#
b01001010001 &
#1187
0#
#1188
1#
b01001010010 &
#1189
0#
#1190
1#
b01001010011 &
#1191
0#
#1192
1#
b01001010100 &
#1193
0#
#1194
1#
b01001010101 &
#1195
0#
#1196
1#
b01001010110 &
#1197
0#
#1198
1#
b01001010111 &
#1199
0#
#1200
1#
b01001011000 &
#1201
0#
#1202
1#
b01001011001 &
#1203
0#
#1204
1#
b01001011010 &
#1205
0#
#1206
1#
b01001011011 &
#1207
0#
#1208
1#
b01001011100 &
#1209
0#
#1210
1#
b01001011101 &
#1211
0#
#1212
1#
b01001011110 &
#1213
0#
#1214
1#
b01001011111 &
#1215
0#
#1216
1#
b01001100000 &
#1217
0#
#1218
1#
b01001100001 &
#1219
0#
#1220
1#
b01001100010 &
#1221
0#
#1222
1#
b01001100011 &
#1223
0#
#1224
1#
b01001100100 &
#1225
0#
#1226
1#
b01001100101 &
#1227
0#
#1228
1#
b01001100110 &
#1229
0#
#1230
1#
b01001100111 &
#1231
0#
#1232
1#
b01001101000 &
#1233
0#
#1234
1#
b01001101001 &
#1235
0#
#1236
1#
b01001101010 &
#1237
0#
#1238
1#
b01001101011 &
#1239
0#
#1240
1#
b01001101100 &
#1241
0#
#1242
1#
b01001101101 &
#1243
0#
#1244
1#
b01001101110 &
#1245
0#
#1246
1#
b01001101111 &
#1247
0#
#1248
1#
b01001110000 &
#1249
0#
#1250
1#
b01001110001 &
#1251
0#
#1252
1#
b01001110010 &
#1253
0#
#1254
1#
b01001110011 &
#1255
0#
#1256
1#
b01001110100 &
#1257
0#
#1258
1#
b01001110101 &
#1259
0#
#1260
1#
b01001110110 &
#1261
0#
#1262
1#
b01001110111 &
#1263
0#
#1264
1#
b01001111000 &
#1265
0#
#1266
1#
b01001111001 &
#1267
0#
#1268
1#
b01001111010 &
#1269
0#
#1270
1#
b01001111011 &
#1271
0#
#1272
1#
b01001111100 &
#1273
0#
#1274
1#
b01001111101 &
#1275
0#
#1276
1#
b01001111110 &
#1277
0#
#1278
1#
b01001111111 &
#1279
0#
#1280
1#
b01010000000 &
#1281
0#
#1282
1#
b01010000001 &
#1283
0#
#1284
1#
b01010000010 &
#1285
0#
#1286
1#
b01010000011 &
#1287
0#
#1288
1#
b01010000100 &
#1289
0#
#1290
1#
b01010000101 &
#1291
0#
#1292
1#
b01010000110 &
#1293
0#
#1294
1#
b01010000111 &
#1295
0#
#1296
1#
b01010001000 &
#1297
0#
#1298
1#
b01010001001 &
#1299
0#
#1300
1#
b01010001010 &
#1301
0#
#1302
1#
b01010001011 &
#1303
0#
#1304
1#
b01010001100 &
#1305
0#
#1306
1#
b01010001101 &
#1307
0#
#1308
1#
b01010001110 &
#1309
0#
#1310
1#
b01010001111 &
#1311
0#
#1312
1#
b01010010000 &
#1313
0#
#1314
1#
b01010010001 &
#1315
0#
#1316
1#
b01010010010 &
#1317
0#
#1318
1#
b01010010011 &
#1319
0#
#1320
1#
b01010010100 &
#1321
0#
#1322
1#
b01010010101 &
#1323
0#
#1324
1#
b01010010110 &
#1325
0#
#1326
1#
b01010010111 &
#1327
0#
#1328
1#
b01010011000 &
#1329
0#
#1330
1#
b01010011001 &
#1331
0#
#1332
1#
b01010011010 &
#1333
0#
#1334
1#
b01010011011 &
#1335
0#
#1336
1#
b01010011100 &
#1337
0#
#1338
1#
b01010011101 &
#1339
0#
#1340
1#
b01010011110 &
#1341
0#
#1342
1#
b01010011111 &
#1343
0#
#1344
1#
b01010100000 &
#1345
0#
#1346
1#
b01010100001 &
#1347
0#
#1348
1#
b01010100010 &
#1349
0#
#1350
1#
b01010100011 &
#1351
0#
#1352
1#
b01010100100 &
#1353
0#
#1354
1#
b01010100101 &
#1355
0#
#1356
1#
b01010100110 &
#1357
0#
#1358
1#
b01010100111 &
#1359
0#
#1360
1#
b01010101000 &
#1361
0#
#1362
1#
b01010101001 &
#1363
0#
#1364
1#
b01010101010 &
#1365
0#
#1366
1#
b01010101011 &
#1367
0#
#1368
1#
b01010101100 &
#1369
0#
#1370
1#
b01010101101 &
#1371
0#
#1372
1#
b01010101110 &
#1373
0#
#1374
1#
b01010101111 &
#1375
0#
#1376
1#
b01010110000 &
#1377
0#
#1378
1#
b01010110001 &
#1379
0#
#1380
1#
b01010110010 &
#1381
0#
#1382
1#
b01010110011 &
#1383
0#
#1384
1#
b01010110100 &
#1385
0#
#1386
1#
b01010110101 &
#1387
0#
#1388
1#
b01010110110 &
#1389
0#
#1390
1#
b01010110111 &
#1391
0#
#1392
1#
b01010111000 &
#1393
0#
#1394
1#
b01010111001 &
#1395
0#
#1396
1#
b01010111010 &
#1397
0#
#1398
1#
b01010111011 &
#1399
0#
#1400
1#
b01010111100 &
#1401
0#
#1402
1#
b01010111101 &
#1403
0#
#1404
1#
b01010111110 &
#1405
0#
#1406
1#
b01010111111 &
#1407
0#
#1408
1#
b01011000000 &
#1409
0#
#1410
1#
b01011000001 &
#1411
0#
#1412
1#
b01011000010 &
#1413
0#
#1414
1#
b01011000011 &
#1415
0#
