receiver.v
`default_nettype none

module receiver(
    i_clk,
    i_rx,
    o_data,
    busy
);
    input wire i_clk;
    input wire i_rx;
    output reg busy;
    output reg[7:0] o_data;

    reg continue_rx;
    reg[7:0] s_data;
    reg[3:0] bit_counter;

    always @ (negedge i_clk, negedge i_rx) begin
        if (continue_rx) begin
            s_data <= s_data >> 1;
            s_data[7] <= i_rx;

            busy <= 1;
            bit_counter <= bit_counter + 1;
            continue_rx <= (bit_counter < 7) ? 1'b1 : 1'b0;
            o_data <= 0;
        end else if (~i_rx) begin
            continue_rx <= 1;
            bit_counter <= 0;
            s_data <= 0;
            busy <= 1;
            o_data <= 0;
        end else begin
            o_data <= s_data;
            busy <= 0;
        end
    end
endmodule

receiver-trace.vcd
$version Generated by VerilatedVcd $end
$timescale 1ps $end
 $scope module TOP $end
  $var wire 1 & i_clk $end
  $var wire 1 ' i_rx $end
  $var wire 1 ( busy $end
  $var wire 8 ) o_data [7:0] $end
  $scope module receiver $end
   $var wire 1 & i_clk $end
   $var wire 1 ' i_rx $end
   $var wire 1 ( busy $end
   $var wire 8 ) o_data [7:0] $end
   $var wire 1 # continue_rx $end
   $var wire 8 $ s_data [7:0] $end
   $var wire 4 % bit_counter [3:0] $end
  $upscope $end
 $upscope $end
$enddefinitions $end


#0
0#
b00000000 $
b0000 %
1&
1'
0(
b00000000 )
#1
0&
#2
1&
#3
0&
#4
1&
#5
0&
#6
1&
#7
0&
#8
1&
#9
0&
#10
1&
#11
0&
#12
1&
#13
0&
#14
1&
#15
0&
#16
1&
#17
0&
#18
1&
#19
0&
#20
1&
#21
0&
#22
1&
#23
0&
#24
1&
#25
0&
#26
1&
#27
0&
#28
1&
#29
0&
#30
1&
#31
0&
#32
1&
#33
0&
#34
1&
#35
0&
#36
1&
#37
1#
0&
0'
1(
#38
1&
#39
b10000000 $
b0001 %
0&
1'
#40
1&
#41
b01000000 $
b0010 %
0&
0'
#42
1&
#43
b10100000 $
b0011 %
0&
1'
#44
1&
#45
b11010000 $
b0100 %
0&
#46
1&
#47
b01101000 $
b0101 %
0&
0'
#48
1&
#49
b00110100 $
b0110 %
0&
#50
1&
#51
b00011010 $
b0111 %
0&
#52
1&
#53
0#
b00001101 $
b1000 %
0&
#54
1&
#55
0&
1'
0(
b00001101 )
