transmitter.v
`default_nettype none

module transmitter(
    i_clk,
    i_tx,
    i_data,
    o_data,
    busy
);
    input wire i_clk;
    input wire i_tx;
    input wire[7:0] i_data;

    output reg busy;
    output reg o_data;

    reg continue_tx;
    reg[9:0] s_data;
    reg[3:0] bit_counter;

    always @ (posedge i_clk, posedge i_tx) begin
        if (i_tx) begin
            continue_tx <= 1;
            bit_counter <= 0;
            s_data <= {1'b1, i_data, 1'b0};
            busy <= 1;
            o_data <= 1;
        end else if (continue_tx) begin
            o_data <= s_data[0];
            s_data <= s_data >> 1;

            busy <= 1;
            bit_counter <= bit_counter + 1;
            continue_tx <= (bit_counter < 9) ? 1'b1 : 1'b0;
        end else begin
            o_data <= 1;
            busy <= 0;
        end
    end
endmodule

transmitter-trace.vcd
$version Generated by VerilatedVcd $end
$timescale 1ps $end
 $scope module TOP $end
  $var wire 1 & i_clk $end
  $var wire 1 ' i_tx $end
  $var wire 8 ( i_data [7:0] $end
  $var wire 1 ) busy $end
  $var wire 1 * o_data $end
  $scope module transmitter $end
   $var wire 1 & i_clk $end
   $var wire 1 ' i_tx $end
   $var wire 8 ( i_data [7:0] $end
   $var wire 1 ) busy $end
   $var wire 1 * o_data $end
   $var wire 1 # continue_tx $end
   $var wire 10 $ s_data [9:0] $end
   $var wire 4 % bit_counter [3:0] $end
  $upscope $end
 $upscope $end
$enddefinitions $end


#0
0#
b0000000000 $
b0000 %
1&
0'
b00000000 (
0)
0*
#1
0&
#2
1&
1*
#3
0&
#4
1&
#5
0&
#6
1&
#7
0&
#8
1&
#9
0&
#10
1&
#11
0&
#12
1&
#13
0&
#14
1&
#15
0&
#16
1&
#17
0&
#18
1&
#19
0&
#20
1&
#21
0&
#22
1&
#23
0&
#24
1&
#25
0&
#26
1&
#27
0&
#28
1&
#29
0&
#30
1&
#31
0&
#32
1&
#33
0&
#34
1&
#35
0&
#36
1&
#37
1#
b1000011010 $
0&
1'
b00001101 (
1)
#38
b0100001101 $
b0001 %
1&
0'
b00000000 (
0*
#39
0&
#40
b0010000110 $
b0010 %
1&
1*
#41
0&
#42
b0001000011 $
b0011 %
1&
0*
#43
0&
#44
b0000100001 $
b0100 %
1&
1*
#45
0&
#46
b0000010000 $
b0101 %
1&
#47
0&
#48
b0000001000 $
b0110 %
1&
0*
#49
0&
#50
b0000000100 $
b0111 %
1&
#51
0&
#52
b0000000010 $
b1000 %
1&
#53
0&
#54
b0000000001 $
b1001 %
1&
#55
0&
#56
0#
b0000000000 $
b1010 %
1&
1*
#57
0&
#58
1&
0)
